<?xml version="1.0" encoding="windows-1252"?>
<XMI xmi.version="1.1" xmlns:UML="omg.org/UML1.3" timestamp="2014-05-14 22:45:18">
	<XMI.header>
		<XMI.documentation>
			<XMI.exporter>Enterprise Architect</XMI.exporter>
			<XMI.exporterVersion>2.5</XMI.exporterVersion>
		</XMI.documentation>
	</XMI.header>
	<XMI.content>
		<UML:Model name="EA Model" xmi.id="MX_EAID_31369CB7_0938_42b0_A86E_1BA661D67FD7">
			<UML:Namespace.ownedElement>
				<UML:Type name="Component Model" xmi.id="EAPK_31369CB7_0938_42b0_A86E_1BA661D67FD7" isRoot="false" isLeaf="false" isAbstract="false" visibility="public">
					<UML:ModelElement.taggedValue>
						<UML:TaggedValue tag="parent" value="EAPK_E4DF5572_ECE3_484a_BAA0_1A9670B4A32E"/>
						<UML:TaggedValue tag="ea_package_id" value="5"/>
						<UML:TaggedValue tag="created" value="2014-05-13 12:05:26"/>
						<UML:TaggedValue tag="modified" value="2014-05-13 12:05:26"/>
						<UML:TaggedValue tag="iscontrolled" value="FALSE"/>
						<UML:TaggedValue tag="lastloaddate" value="2014-05-13 12:05:26"/>
						<UML:TaggedValue tag="lastsavedate" value="2014-05-13 12:05:26"/>
						<UML:TaggedValue tag="isprotected" value="FALSE"/>
						<UML:TaggedValue tag="usedtd" value="FALSE"/>
						<UML:TaggedValue tag="logxml" value="FALSE"/>
						<UML:TaggedValue tag="tpos" value="7"/>
						<UML:TaggedValue tag="packageFlags" value="isModel=1;VICON=4;CRC=0;"/>
						<UML:TaggedValue tag="batchsave" value="0"/>
						<UML:TaggedValue tag="batchload" value="0"/>
						<UML:TaggedValue tag="phase" value="1.0"/>
						<UML:TaggedValue tag="status" value="Proposed"/>
						<UML:TaggedValue tag="complexity" value="1"/>
						<UML:TaggedValue tag="ea_stype" value="Public"/>
						<UML:TaggedValue tag="tpos" value="7"/>
					</UML:ModelElement.taggedValue>
					<UML:Namespace.ownedElement>
						<UML:Component name="RegionBFilter" xmi.id="EAID_10EA6DFD_15B5_4de7_AA8D_E6E18301E274" visibility="public" namespace="EAPK_31369CB7_0938_42b0_A86E_1BA661D67FD7" isRoot="false" isLeaf="false" isAbstract="false">
							<UML:ModelElement.stereotype>
								<UML:Stereotype name="Component"/>
							</UML:ModelElement.stereotype>
							<UML:ModelElement.taggedValue>
								<UML:TaggedValue tag="isSpecification" value="false"/>
								<UML:TaggedValue tag="ea_stype" value="Component"/>
								<UML:TaggedValue tag="ea_ntype" value="0"/>
								<UML:TaggedValue tag="version" value="1.0"/>
								<UML:TaggedValue tag="isActive" value="false"/>
								<UML:TaggedValue tag="package" value="EAPK_31369CB7_0938_42b0_A86E_1BA661D67FD7"/>
								<UML:TaggedValue tag="date_created" value="2014-05-13 12:16:35"/>
								<UML:TaggedValue tag="date_modified" value="2014-05-13 12:17:12"/>
								<UML:TaggedValue tag="gentype" value="Java"/>
								<UML:TaggedValue tag="tagged" value="0"/>
								<UML:TaggedValue tag="package_name" value="Component Model"/>
								<UML:TaggedValue tag="phase" value="1.0"/>
								<UML:TaggedValue tag="author" value="soo"/>
								<UML:TaggedValue tag="complexity" value="1"/>
								<UML:TaggedValue tag="status" value="Proposed"/>
								<UML:TaggedValue tag="stereotype" value="Component"/>
								<UML:TaggedValue tag="tpos" value="0"/>
								<UML:TaggedValue tag="ea_localid" value="53"/>
								<UML:TaggedValue tag="ea_eleType" value="element"/>
								<UML:TaggedValue tag="style" value="BackColor=-1;BorderColor=-1;BorderWidth=-1;FontColor=-1;VSwimLanes=1;HSwimLanes=1;BorderStyle=0;"/>
								<UML:TaggedValue tag="$ea_xref_property" value="$XREFPROP=$XID={87B85F72-F8D8-4c07-BD5E-9C82694D5F6C}$XID;$NAM=Stereotypes$NAM;$TYP=element property$TYP;$VIS=Public$VIS;$PAR=0$PAR;$DES=@STEREO;Name=Component;@ENDSTEREO;$DES;$CLT={10EA6DFD-15B5-4de7-AA8D-E6E18301E274}$CLT;$SUP=&lt;none&gt;$SUP;$ENDXREF;"/>
							</UML:ModelElement.taggedValue>
						</UML:Component>
						<UML:Association xmi.id="EAID_7709F01B_C088_4d80_AA83_D51EDEEEBA8B" visibility="public" isRoot="false" isLeaf="false" isAbstract="false" client="EAID_10EA6DFD_15B5_4de7_AA8D_E6E18301E274" supplier="EAID_47743406_C904_4c4a_A09C_5AD9C4848CB6">
							<UML:ModelElement.taggedValue>
								<UML:TaggedValue tag="style" value="3"/>
								<UML:TaggedValue tag="ea_type" value="Association"/>
								<UML:TaggedValue tag="direction" value="Unspecified"/>
								<UML:TaggedValue tag="linemode" value="3"/>
								<UML:TaggedValue tag="linecolor" value="-1"/>
								<UML:TaggedValue tag="linewidth" value="0"/>
								<UML:TaggedValue tag="seqno" value="0"/>
								<UML:TaggedValue tag="headStyle" value="0"/>
								<UML:TaggedValue tag="lineStyle" value="0"/>
								<UML:TaggedValue tag="ea_localid" value="34"/>
								<UML:TaggedValue tag="ea_sourceName" value="RegionBFilter"/>
								<UML:TaggedValue tag="ea_targetName" value="Pipe"/>
								<UML:TaggedValue tag="ea_sourceType" value="Component"/>
								<UML:TaggedValue tag="ea_targetType" value="Component"/>
								<UML:TaggedValue tag="ea_sourceID" value="53"/>
								<UML:TaggedValue tag="ea_targetID" value="54"/>
								<UML:TaggedValue tag="virtualInheritance" value="0"/>
							</UML:ModelElement.taggedValue>
							<UML:Association.connection>
								<UML:AssociationEnd visibility="public" aggregation="none" isOrdered="false" targetScope="instance" changeable="none" isNavigable="true" type="EAID_10EA6DFD_15B5_4de7_AA8D_E6E18301E274">
									<UML:ModelElement.taggedValue>
										<UML:TaggedValue tag="containment" value="Unspecified"/>
										<UML:TaggedValue tag="sourcestyle" value="Union=0;Derived=0;AllowDuplicates=0;Owned=0;Navigable=Unspecified;"/>
										<UML:TaggedValue tag="ea_end" value="source"/>
									</UML:ModelElement.taggedValue>
								</UML:AssociationEnd>
								<UML:AssociationEnd visibility="public" aggregation="none" isOrdered="false" targetScope="instance" changeable="none" isNavigable="true" type="EAID_47743406_C904_4c4a_A09C_5AD9C4848CB6">
									<UML:ModelElement.taggedValue>
										<UML:TaggedValue tag="containment" value="Unspecified"/>
										<UML:TaggedValue tag="deststyle" value="Union=0;Derived=0;AllowDuplicates=0;Owned=0;Navigable=Unspecified;"/>
										<UML:TaggedValue tag="ea_end" value="target"/>
									</UML:ModelElement.taggedValue>
								</UML:AssociationEnd>
							</UML:Association.connection>
						</UML:Association>
						<UML:Association xmi.id="EAID_E039CA5A_A07F_483c_94EE_FDCF2C522F93" visibility="public" isRoot="false" isLeaf="false" isAbstract="false" client="EAID_950B5493_F09B_401a_AFAA_C297AD96AB2E" supplier="EAID_10EA6DFD_15B5_4de7_AA8D_E6E18301E274">
							<UML:ModelElement.taggedValue>
								<UML:TaggedValue tag="style" value="3"/>
								<UML:TaggedValue tag="ea_type" value="Association"/>
								<UML:TaggedValue tag="direction" value="Unspecified"/>
								<UML:TaggedValue tag="linemode" value="3"/>
								<UML:TaggedValue tag="linecolor" value="-1"/>
								<UML:TaggedValue tag="linewidth" value="0"/>
								<UML:TaggedValue tag="seqno" value="0"/>
								<UML:TaggedValue tag="headStyle" value="0"/>
								<UML:TaggedValue tag="lineStyle" value="0"/>
								<UML:TaggedValue tag="ea_localid" value="33"/>
								<UML:TaggedValue tag="ea_sourceName" value="Pipe"/>
								<UML:TaggedValue tag="ea_targetName" value="RegionBFilter"/>
								<UML:TaggedValue tag="ea_sourceType" value="Component"/>
								<UML:TaggedValue tag="ea_targetType" value="Component"/>
								<UML:TaggedValue tag="ea_sourceID" value="52"/>
								<UML:TaggedValue tag="ea_targetID" value="53"/>
								<UML:TaggedValue tag="virtualInheritance" value="0"/>
							</UML:ModelElement.taggedValue>
							<UML:Association.connection>
								<UML:AssociationEnd visibility="public" aggregation="none" isOrdered="false" targetScope="instance" changeable="none" isNavigable="true" type="EAID_950B5493_F09B_401a_AFAA_C297AD96AB2E">
									<UML:ModelElement.taggedValue>
										<UML:TaggedValue tag="containment" value="Unspecified"/>
										<UML:TaggedValue tag="sourcestyle" value="Union=0;Derived=0;AllowDuplicates=0;Owned=0;Navigable=Unspecified;"/>
										<UML:TaggedValue tag="ea_end" value="source"/>
									</UML:ModelElement.taggedValue>
								</UML:AssociationEnd>
								<UML:AssociationEnd visibility="public" aggregation="none" isOrdered="false" targetScope="instance" changeable="none" isNavigable="true" type="EAID_10EA6DFD_15B5_4de7_AA8D_E6E18301E274">
									<UML:ModelElement.taggedValue>
										<UML:TaggedValue tag="containment" value="Unspecified"/>
										<UML:TaggedValue tag="deststyle" value="Union=0;Derived=0;AllowDuplicates=0;Owned=0;Navigable=Unspecified;"/>
										<UML:TaggedValue tag="ea_end" value="target"/>
									</UML:ModelElement.taggedValue>
								</UML:AssociationEnd>
							</UML:Association.connection>
						</UML:Association>
						<UML:Connector name="Pipe" xmi.id="EAID_47743406_C904_4c4a_A09C_5AD9C4848CB6" visibility="public" namespace="EAPK_31369CB7_0938_42b0_A86E_1BA661D67FD7" isRoot="false" isLeaf="false" isAbstract="false">
							<UML:ModelElement.stereotype>
								<UML:Stereotype name="Connector"/>
							</UML:ModelElement.stereotype>
							<UML:ModelElement.taggedValue>
								<UML:TaggedValue tag="isSpecification" value="false"/>
								<UML:TaggedValue tag="ea_stype" value="Component"/>
								<UML:TaggedValue tag="ea_ntype" value="0"/>
								<UML:TaggedValue tag="version" value="1.0"/>
								<UML:TaggedValue tag="isActive" value="false"/>
								<UML:TaggedValue tag="package" value="EAPK_31369CB7_0938_42b0_A86E_1BA661D67FD7"/>
								<UML:TaggedValue tag="date_created" value="2014-05-13 12:16:36"/>
								<UML:TaggedValue tag="date_modified" value="2014-05-13 12:17:56"/>
								<UML:TaggedValue tag="gentype" value="Java"/>
								<UML:TaggedValue tag="tagged" value="0"/>
								<UML:TaggedValue tag="package_name" value="Component Model"/>
								<UML:TaggedValue tag="phase" value="1.0"/>
								<UML:TaggedValue tag="author" value="soo"/>
								<UML:TaggedValue tag="complexity" value="1"/>
								<UML:TaggedValue tag="status" value="Proposed"/>
								<UML:TaggedValue tag="stereotype" value="Connector"/>
								<UML:TaggedValue tag="tpos" value="0"/>
								<UML:TaggedValue tag="ea_localid" value="54"/>
								<UML:TaggedValue tag="ea_eleType" value="element"/>
								<UML:TaggedValue tag="style" value="BackColor=-1;BorderColor=-1;BorderWidth=-1;FontColor=-1;VSwimLanes=1;HSwimLanes=1;BorderStyle=0;"/>
								<UML:TaggedValue tag="$ea_xref_property" value="$XREFPROP=$XID={C8A7EA9E-6A1C-4cf5-9F6D-77427CEADBD5}$XID;$NAM=Stereotypes$NAM;$TYP=element property$TYP;$VIS=Public$VIS;$PAR=0$PAR;$DES=@STEREO;Name=Connector;@ENDSTEREO;$DES;$CLT={47743406-C904-4c4a-A09C-5AD9C4848CB6}$CLT;$SUP=&lt;none&gt;$SUP;$ENDXREF;"/>
							</UML:ModelElement.taggedValue>
						</UML:Connector>
						<UML:Association xmi.id="EAID_3DD4086F_0665_4442_A9E8_8872D1243BE6" visibility="public" isRoot="false" isLeaf="false" isAbstract="false" client="EAID_47743406_C904_4c4a_A09C_5AD9C4848CB6" supplier="EAID_D6018000_7990_45a4_8FC9_0793FFBC65B2">
							<UML:ModelElement.taggedValue>
								<UML:TaggedValue tag="style" value="3"/>
								<UML:TaggedValue tag="ea_type" value="Association"/>
								<UML:TaggedValue tag="direction" value="Unspecified"/>
								<UML:TaggedValue tag="linemode" value="3"/>
								<UML:TaggedValue tag="linecolor" value="-1"/>
								<UML:TaggedValue tag="linewidth" value="0"/>
								<UML:TaggedValue tag="seqno" value="0"/>
								<UML:TaggedValue tag="headStyle" value="0"/>
								<UML:TaggedValue tag="lineStyle" value="0"/>
								<UML:TaggedValue tag="ea_localid" value="35"/>
								<UML:TaggedValue tag="ea_sourceName" value="Pipe"/>
								<UML:TaggedValue tag="ea_targetName" value="RegionBSinkFilter"/>
								<UML:TaggedValue tag="ea_sourceType" value="Component"/>
								<UML:TaggedValue tag="ea_targetType" value="Component"/>
								<UML:TaggedValue tag="ea_sourceID" value="54"/>
								<UML:TaggedValue tag="ea_targetID" value="55"/>
								<UML:TaggedValue tag="virtualInheritance" value="0"/>
							</UML:ModelElement.taggedValue>
							<UML:Association.connection>
								<UML:AssociationEnd visibility="public" aggregation="none" isOrdered="false" targetScope="instance" changeable="none" isNavigable="true" type="EAID_47743406_C904_4c4a_A09C_5AD9C4848CB6">
									<UML:ModelElement.taggedValue>
										<UML:TaggedValue tag="containment" value="Unspecified"/>
										<UML:TaggedValue tag="sourcestyle" value="Union=0;Derived=0;AllowDuplicates=0;Owned=0;Navigable=Unspecified;"/>
										<UML:TaggedValue tag="ea_end" value="source"/>
									</UML:ModelElement.taggedValue>
								</UML:AssociationEnd>
								<UML:AssociationEnd visibility="public" aggregation="none" isOrdered="false" targetScope="instance" changeable="none" isNavigable="true" type="EAID_D6018000_7990_45a4_8FC9_0793FFBC65B2">
									<UML:ModelElement.taggedValue>
										<UML:TaggedValue tag="containment" value="Unspecified"/>
										<UML:TaggedValue tag="deststyle" value="Union=0;Derived=0;AllowDuplicates=0;Owned=0;Navigable=Unspecified;"/>
										<UML:TaggedValue tag="ea_end" value="target"/>
									</UML:ModelElement.taggedValue>
								</UML:AssociationEnd>
							</UML:Association.connection>
						</UML:Association>
						<UML:Connector name="Pipe" xmi.id="EAID_5BFC3086_2EA4_4908_890E_E6F601EEC73C" visibility="public" namespace="EAPK_31369CB7_0938_42b0_A86E_1BA661D67FD7" isRoot="false" isLeaf="false" isAbstract="false">
							<UML:ModelElement.stereotype>
								<UML:Stereotype name="Connector"/>
							</UML:ModelElement.stereotype>
							<UML:ModelElement.taggedValue>
								<UML:TaggedValue tag="isSpecification" value="false"/>
								<UML:TaggedValue tag="ea_stype" value="Component"/>
								<UML:TaggedValue tag="ea_ntype" value="0"/>
								<UML:TaggedValue tag="version" value="1.0"/>
								<UML:TaggedValue tag="isActive" value="false"/>
								<UML:TaggedValue tag="package" value="EAPK_31369CB7_0938_42b0_A86E_1BA661D67FD7"/>
								<UML:TaggedValue tag="date_created" value="2014-05-13 12:16:20"/>
								<UML:TaggedValue tag="date_modified" value="2014-05-13 12:17:50"/>
								<UML:TaggedValue tag="gentype" value="Java"/>
								<UML:TaggedValue tag="tagged" value="0"/>
								<UML:TaggedValue tag="package_name" value="Component Model"/>
								<UML:TaggedValue tag="phase" value="1.0"/>
								<UML:TaggedValue tag="author" value="soo"/>
								<UML:TaggedValue tag="complexity" value="1"/>
								<UML:TaggedValue tag="status" value="Proposed"/>
								<UML:TaggedValue tag="stereotype" value="Connector"/>
								<UML:TaggedValue tag="tpos" value="0"/>
								<UML:TaggedValue tag="ea_localid" value="50"/>
								<UML:TaggedValue tag="ea_eleType" value="element"/>
								<UML:TaggedValue tag="style" value="BackColor=-1;BorderColor=-1;BorderWidth=-1;FontColor=-1;VSwimLanes=1;HSwimLanes=1;BorderStyle=0;"/>
								<UML:TaggedValue tag="$ea_xref_property" value="$XREFPROP=$XID={FCA9690A-C5A7-4a47-86CB-FE9E96118C89}$XID;$NAM=Stereotypes$NAM;$TYP=element property$TYP;$VIS=Public$VIS;$PAR=0$PAR;$DES=@STEREO;Name=Connector;@ENDSTEREO;$DES;$CLT={5BFC3086-2EA4-4908-890E-E6F601EEC73C}$CLT;$SUP=&lt;none&gt;$SUP;$ENDXREF;"/>
							</UML:ModelElement.taggedValue>
						</UML:Connector>
						<UML:Association xmi.id="EAID_36B9C420_1E2C_4507_924C_D97B45E9A480" visibility="public" isRoot="false" isLeaf="false" isAbstract="false" client="EAID_669D5D5F_F9EB_4b1b_A50A_07799E4FCBE5" supplier="EAID_5BFC3086_2EA4_4908_890E_E6F601EEC73C">
							<UML:ModelElement.taggedValue>
								<UML:TaggedValue tag="style" value="3"/>
								<UML:TaggedValue tag="ea_type" value="Association"/>
								<UML:TaggedValue tag="direction" value="Unspecified"/>
								<UML:TaggedValue tag="linemode" value="3"/>
								<UML:TaggedValue tag="linecolor" value="-1"/>
								<UML:TaggedValue tag="linewidth" value="0"/>
								<UML:TaggedValue tag="seqno" value="0"/>
								<UML:TaggedValue tag="headStyle" value="0"/>
								<UML:TaggedValue tag="lineStyle" value="0"/>
								<UML:TaggedValue tag="ea_localid" value="37"/>
								<UML:TaggedValue tag="ea_sourceName" value="RegionAFilter"/>
								<UML:TaggedValue tag="ea_targetName" value="Pipe"/>
								<UML:TaggedValue tag="ea_sourceType" value="Component"/>
								<UML:TaggedValue tag="ea_targetType" value="Component"/>
								<UML:TaggedValue tag="ea_sourceID" value="49"/>
								<UML:TaggedValue tag="ea_targetID" value="50"/>
								<UML:TaggedValue tag="virtualInheritance" value="0"/>
							</UML:ModelElement.taggedValue>
							<UML:Association.connection>
								<UML:AssociationEnd visibility="public" aggregation="none" isOrdered="false" targetScope="instance" changeable="none" isNavigable="true" type="EAID_669D5D5F_F9EB_4b1b_A50A_07799E4FCBE5">
									<UML:ModelElement.taggedValue>
										<UML:TaggedValue tag="containment" value="Unspecified"/>
										<UML:TaggedValue tag="sourcestyle" value="Union=0;Derived=0;AllowDuplicates=0;Owned=0;Navigable=Unspecified;"/>
										<UML:TaggedValue tag="ea_end" value="source"/>
									</UML:ModelElement.taggedValue>
								</UML:AssociationEnd>
								<UML:AssociationEnd visibility="public" aggregation="none" isOrdered="false" targetScope="instance" changeable="none" isNavigable="true" type="EAID_5BFC3086_2EA4_4908_890E_E6F601EEC73C">
									<UML:ModelElement.taggedValue>
										<UML:TaggedValue tag="containment" value="Unspecified"/>
										<UML:TaggedValue tag="deststyle" value="Union=0;Derived=0;AllowDuplicates=0;Owned=0;Navigable=Unspecified;"/>
										<UML:TaggedValue tag="ea_end" value="target"/>
									</UML:ModelElement.taggedValue>
								</UML:AssociationEnd>
							</UML:Association.connection>
						</UML:Association>
						<UML:Association xmi.id="EAID_59040C4C_F485_41e7_B05E_9FE5FC0C45FB" visibility="public" isRoot="false" isLeaf="false" isAbstract="false" client="EAID_5BFC3086_2EA4_4908_890E_E6F601EEC73C" supplier="EAID_BE63FCEB_C8DF_4c7c_98A6_DB730CA80D42">
							<UML:ModelElement.taggedValue>
								<UML:TaggedValue tag="style" value="3"/>
								<UML:TaggedValue tag="ea_type" value="Association"/>
								<UML:TaggedValue tag="direction" value="Unspecified"/>
								<UML:TaggedValue tag="linemode" value="3"/>
								<UML:TaggedValue tag="linecolor" value="-1"/>
								<UML:TaggedValue tag="linewidth" value="0"/>
								<UML:TaggedValue tag="seqno" value="0"/>
								<UML:TaggedValue tag="headStyle" value="0"/>
								<UML:TaggedValue tag="lineStyle" value="0"/>
								<UML:TaggedValue tag="ea_localid" value="38"/>
								<UML:TaggedValue tag="ea_sourceName" value="Pipe"/>
								<UML:TaggedValue tag="ea_targetName" value="RegionASinkFilter"/>
								<UML:TaggedValue tag="ea_sourceType" value="Component"/>
								<UML:TaggedValue tag="ea_targetType" value="Component"/>
								<UML:TaggedValue tag="ea_sourceID" value="50"/>
								<UML:TaggedValue tag="ea_targetID" value="51"/>
								<UML:TaggedValue tag="virtualInheritance" value="0"/>
							</UML:ModelElement.taggedValue>
							<UML:Association.connection>
								<UML:AssociationEnd visibility="public" aggregation="none" isOrdered="false" targetScope="instance" changeable="none" isNavigable="true" type="EAID_5BFC3086_2EA4_4908_890E_E6F601EEC73C">
									<UML:ModelElement.taggedValue>
										<UML:TaggedValue tag="containment" value="Unspecified"/>
										<UML:TaggedValue tag="sourcestyle" value="Union=0;Derived=0;AllowDuplicates=0;Owned=0;Navigable=Unspecified;"/>
										<UML:TaggedValue tag="ea_end" value="source"/>
									</UML:ModelElement.taggedValue>
								</UML:AssociationEnd>
								<UML:AssociationEnd visibility="public" aggregation="none" isOrdered="false" targetScope="instance" changeable="none" isNavigable="true" type="EAID_BE63FCEB_C8DF_4c7c_98A6_DB730CA80D42">
									<UML:ModelElement.taggedValue>
										<UML:TaggedValue tag="containment" value="Unspecified"/>
										<UML:TaggedValue tag="deststyle" value="Union=0;Derived=0;AllowDuplicates=0;Owned=0;Navigable=Unspecified;"/>
										<UML:TaggedValue tag="ea_end" value="target"/>
									</UML:ModelElement.taggedValue>
								</UML:AssociationEnd>
							</UML:Association.connection>
						</UML:Association>
						<UML:Component name="RegionAFilter" xmi.id="EAID_669D5D5F_F9EB_4b1b_A50A_07799E4FCBE5" visibility="public" namespace="EAPK_31369CB7_0938_42b0_A86E_1BA661D67FD7" isRoot="false" isLeaf="false" isAbstract="false">
							<UML:ModelElement.stereotype>
								<UML:Stereotype name="Component"/>
							</UML:ModelElement.stereotype>
							<UML:ModelElement.taggedValue>
								<UML:TaggedValue tag="isSpecification" value="false"/>
								<UML:TaggedValue tag="ea_stype" value="Component"/>
								<UML:TaggedValue tag="ea_ntype" value="0"/>
								<UML:TaggedValue tag="version" value="1.0"/>
								<UML:TaggedValue tag="isActive" value="false"/>
								<UML:TaggedValue tag="package" value="EAPK_31369CB7_0938_42b0_A86E_1BA661D67FD7"/>
								<UML:TaggedValue tag="date_created" value="2014-05-13 12:16:13"/>
								<UML:TaggedValue tag="date_modified" value="2014-05-13 12:17:05"/>
								<UML:TaggedValue tag="gentype" value="Java"/>
								<UML:TaggedValue tag="tagged" value="0"/>
								<UML:TaggedValue tag="package_name" value="Component Model"/>
								<UML:TaggedValue tag="phase" value="1.0"/>
								<UML:TaggedValue tag="author" value="soo"/>
								<UML:TaggedValue tag="complexity" value="1"/>
								<UML:TaggedValue tag="status" value="Proposed"/>
								<UML:TaggedValue tag="stereotype" value="Component"/>
								<UML:TaggedValue tag="tpos" value="0"/>
								<UML:TaggedValue tag="ea_localid" value="49"/>
								<UML:TaggedValue tag="ea_eleType" value="element"/>
								<UML:TaggedValue tag="style" value="BackColor=-1;BorderColor=-1;BorderWidth=-1;FontColor=-1;VSwimLanes=1;HSwimLanes=1;BorderStyle=0;"/>
								<UML:TaggedValue tag="$ea_xref_property" value="$XREFPROP=$XID={C8482F5A-1B39-46d6-9AF3-22EA103A9FAE}$XID;$NAM=Stereotypes$NAM;$TYP=element property$TYP;$VIS=Public$VIS;$PAR=0$PAR;$DES=@STEREO;Name=Component;@ENDSTEREO;$DES;$CLT={669D5D5F-F9EB-4b1b-A50A-07799E4FCBE5}$CLT;$SUP=&lt;none&gt;$SUP;$ENDXREF;"/>
							</UML:ModelElement.taggedValue>
						</UML:Component>
						<UML:Association xmi.id="EAID_1C3002D7_1E88_4779_A1EC_635E509AFFD2" visibility="public" isRoot="false" isLeaf="false" isAbstract="false" client="EAID_E14DC77C_0C77_4f33_AAC0_071536A15FA8" supplier="EAID_669D5D5F_F9EB_4b1b_A50A_07799E4FCBE5">
							<UML:ModelElement.taggedValue>
								<UML:TaggedValue tag="style" value="3"/>
								<UML:TaggedValue tag="ea_type" value="Association"/>
								<UML:TaggedValue tag="direction" value="Unspecified"/>
								<UML:TaggedValue tag="linemode" value="3"/>
								<UML:TaggedValue tag="linecolor" value="-1"/>
								<UML:TaggedValue tag="linewidth" value="0"/>
								<UML:TaggedValue tag="seqno" value="0"/>
								<UML:TaggedValue tag="headStyle" value="0"/>
								<UML:TaggedValue tag="lineStyle" value="0"/>
								<UML:TaggedValue tag="ea_localid" value="36"/>
								<UML:TaggedValue tag="ea_sourceName" value="Pipe"/>
								<UML:TaggedValue tag="ea_targetName" value="RegionAFilter"/>
								<UML:TaggedValue tag="ea_sourceType" value="Component"/>
								<UML:TaggedValue tag="ea_targetType" value="Component"/>
								<UML:TaggedValue tag="ea_sourceID" value="48"/>
								<UML:TaggedValue tag="ea_targetID" value="49"/>
								<UML:TaggedValue tag="virtualInheritance" value="0"/>
							</UML:ModelElement.taggedValue>
							<UML:Association.connection>
								<UML:AssociationEnd visibility="public" aggregation="none" isOrdered="false" targetScope="instance" changeable="none" isNavigable="true" type="EAID_E14DC77C_0C77_4f33_AAC0_071536A15FA8">
									<UML:ModelElement.taggedValue>
										<UML:TaggedValue tag="containment" value="Unspecified"/>
										<UML:TaggedValue tag="sourcestyle" value="Union=0;Derived=0;AllowDuplicates=0;Owned=0;Navigable=Unspecified;"/>
										<UML:TaggedValue tag="ea_end" value="source"/>
									</UML:ModelElement.taggedValue>
								</UML:AssociationEnd>
								<UML:AssociationEnd visibility="public" aggregation="none" isOrdered="false" targetScope="instance" changeable="none" isNavigable="true" type="EAID_669D5D5F_F9EB_4b1b_A50A_07799E4FCBE5">
									<UML:ModelElement.taggedValue>
										<UML:TaggedValue tag="containment" value="Unspecified"/>
										<UML:TaggedValue tag="deststyle" value="Union=0;Derived=0;AllowDuplicates=0;Owned=0;Navigable=Unspecified;"/>
										<UML:TaggedValue tag="ea_end" value="target"/>
									</UML:ModelElement.taggedValue>
								</UML:AssociationEnd>
							</UML:Association.connection>
						</UML:Association>
						<UML:Connector name="Pipe" xmi.id="EAID_950B5493_F09B_401a_AFAA_C297AD96AB2E" visibility="public" namespace="EAPK_31369CB7_0938_42b0_A86E_1BA661D67FD7" isRoot="false" isLeaf="false" isAbstract="false">
							<UML:ModelElement.stereotype>
								<UML:Stereotype name="Connector"/>
							</UML:ModelElement.stereotype>
							<UML:ModelElement.taggedValue>
								<UML:TaggedValue tag="isSpecification" value="false"/>
								<UML:TaggedValue tag="ea_stype" value="Component"/>
								<UML:TaggedValue tag="ea_ntype" value="0"/>
								<UML:TaggedValue tag="version" value="1.0"/>
								<UML:TaggedValue tag="isActive" value="false"/>
								<UML:TaggedValue tag="package" value="EAPK_31369CB7_0938_42b0_A86E_1BA661D67FD7"/>
								<UML:TaggedValue tag="date_created" value="2014-05-13 12:16:34"/>
								<UML:TaggedValue tag="date_modified" value="2014-05-13 12:17:46"/>
								<UML:TaggedValue tag="gentype" value="Java"/>
								<UML:TaggedValue tag="tagged" value="0"/>
								<UML:TaggedValue tag="package_name" value="Component Model"/>
								<UML:TaggedValue tag="phase" value="1.0"/>
								<UML:TaggedValue tag="author" value="soo"/>
								<UML:TaggedValue tag="complexity" value="1"/>
								<UML:TaggedValue tag="status" value="Proposed"/>
								<UML:TaggedValue tag="stereotype" value="Connector"/>
								<UML:TaggedValue tag="tpos" value="0"/>
								<UML:TaggedValue tag="ea_localid" value="52"/>
								<UML:TaggedValue tag="ea_eleType" value="element"/>
								<UML:TaggedValue tag="style" value="BackColor=-1;BorderColor=-1;BorderWidth=-1;FontColor=-1;VSwimLanes=1;HSwimLanes=1;BorderStyle=0;"/>
								<UML:TaggedValue tag="$ea_xref_property" value="$XREFPROP=$XID={22519E0B-DC36-48e1-8F9D-2BBB316D99D6}$XID;$NAM=Stereotypes$NAM;$TYP=element property$TYP;$VIS=Public$VIS;$PAR=0$PAR;$DES=@STEREO;Name=Connector;@ENDSTEREO;$DES;$CLT={950B5493-F09B-401a-AFAA-C297AD96AB2E}$CLT;$SUP=&lt;none&gt;$SUP;$ENDXREF;"/>
							</UML:ModelElement.taggedValue>
						</UML:Connector>
						<UML:Association xmi.id="EAID_3B75DB1E_071F_41a4_B33E_B4817D84BC3B" visibility="public" isRoot="false" isLeaf="false" isAbstract="false" client="EAID_CDF3BF72_3AC7_4349_A9F8_E4CA728FED28" supplier="EAID_950B5493_F09B_401a_AFAA_C297AD96AB2E">
							<UML:ModelElement.taggedValue>
								<UML:TaggedValue tag="style" value="3"/>
								<UML:TaggedValue tag="ea_type" value="Association"/>
								<UML:TaggedValue tag="direction" value="Unspecified"/>
								<UML:TaggedValue tag="linemode" value="3"/>
								<UML:TaggedValue tag="linecolor" value="-1"/>
								<UML:TaggedValue tag="linewidth" value="0"/>
								<UML:TaggedValue tag="seqno" value="0"/>
								<UML:TaggedValue tag="headStyle" value="0"/>
								<UML:TaggedValue tag="lineStyle" value="0"/>
								<UML:TaggedValue tag="ea_localid" value="32"/>
								<UML:TaggedValue tag="ea_sourceName" value="SourceFilter"/>
								<UML:TaggedValue tag="ea_targetName" value="Pipe"/>
								<UML:TaggedValue tag="ea_sourceType" value="Component"/>
								<UML:TaggedValue tag="ea_targetType" value="Component"/>
								<UML:TaggedValue tag="ea_sourceID" value="47"/>
								<UML:TaggedValue tag="ea_targetID" value="52"/>
								<UML:TaggedValue tag="virtualInheritance" value="0"/>
							</UML:ModelElement.taggedValue>
							<UML:Association.connection>
								<UML:AssociationEnd visibility="public" aggregation="none" isOrdered="false" targetScope="instance" changeable="none" isNavigable="true" type="EAID_CDF3BF72_3AC7_4349_A9F8_E4CA728FED28">
									<UML:ModelElement.taggedValue>
										<UML:TaggedValue tag="containment" value="Unspecified"/>
										<UML:TaggedValue tag="sourcestyle" value="Union=0;Derived=0;AllowDuplicates=0;Owned=0;Navigable=Unspecified;"/>
										<UML:TaggedValue tag="ea_end" value="source"/>
									</UML:ModelElement.taggedValue>
								</UML:AssociationEnd>
								<UML:AssociationEnd visibility="public" aggregation="none" isOrdered="false" targetScope="instance" changeable="none" isNavigable="true" type="EAID_950B5493_F09B_401a_AFAA_C297AD96AB2E">
									<UML:ModelElement.taggedValue>
										<UML:TaggedValue tag="containment" value="Unspecified"/>
										<UML:TaggedValue tag="deststyle" value="Union=0;Derived=0;AllowDuplicates=0;Owned=0;Navigable=Unspecified;"/>
										<UML:TaggedValue tag="ea_end" value="target"/>
									</UML:ModelElement.taggedValue>
								</UML:AssociationEnd>
							</UML:Association.connection>
						</UML:Association>
						<UML:Component name="RegionASinkFilter" xmi.id="EAID_BE63FCEB_C8DF_4c7c_98A6_DB730CA80D42" visibility="public" namespace="EAPK_31369CB7_0938_42b0_A86E_1BA661D67FD7" isRoot="false" isLeaf="false" isAbstract="false">
							<UML:ModelElement.stereotype>
								<UML:Stereotype name="Component"/>
							</UML:ModelElement.stereotype>
							<UML:ModelElement.taggedValue>
								<UML:TaggedValue tag="isSpecification" value="false"/>
								<UML:TaggedValue tag="ea_stype" value="Component"/>
								<UML:TaggedValue tag="ea_ntype" value="0"/>
								<UML:TaggedValue tag="version" value="1.0"/>
								<UML:TaggedValue tag="isActive" value="false"/>
								<UML:TaggedValue tag="package" value="EAPK_31369CB7_0938_42b0_A86E_1BA661D67FD7"/>
								<UML:TaggedValue tag="date_created" value="2014-05-13 12:16:29"/>
								<UML:TaggedValue tag="date_modified" value="2014-05-13 12:17:19"/>
								<UML:TaggedValue tag="gentype" value="Java"/>
								<UML:TaggedValue tag="tagged" value="0"/>
								<UML:TaggedValue tag="package_name" value="Component Model"/>
								<UML:TaggedValue tag="phase" value="1.0"/>
								<UML:TaggedValue tag="author" value="soo"/>
								<UML:TaggedValue tag="complexity" value="1"/>
								<UML:TaggedValue tag="status" value="Proposed"/>
								<UML:TaggedValue tag="stereotype" value="Component"/>
								<UML:TaggedValue tag="tpos" value="0"/>
								<UML:TaggedValue tag="ea_localid" value="51"/>
								<UML:TaggedValue tag="ea_eleType" value="element"/>
								<UML:TaggedValue tag="style" value="BackColor=-1;BorderColor=-1;BorderWidth=-1;FontColor=-1;VSwimLanes=1;HSwimLanes=1;BorderStyle=0;"/>
								<UML:TaggedValue tag="$ea_xref_property" value="$XREFPROP=$XID={AF22B934-3EB1-46b5-B1B4-2468A565A382}$XID;$NAM=Stereotypes$NAM;$TYP=element property$TYP;$VIS=Public$VIS;$PAR=0$PAR;$DES=@STEREO;Name=Component;@ENDSTEREO;$DES;$CLT={BE63FCEB-C8DF-4c7c-98A6-DB730CA80D42}$CLT;$SUP=&lt;none&gt;$SUP;$ENDXREF;"/>
							</UML:ModelElement.taggedValue>
						</UML:Component>
						<UML:Component name="SourceFilter" xmi.id="EAID_CDF3BF72_3AC7_4349_A9F8_E4CA728FED28" visibility="public" namespace="EAPK_31369CB7_0938_42b0_A86E_1BA661D67FD7" isRoot="false" isLeaf="false" isAbstract="false">
							<UML:ModelElement.stereotype>
								<UML:Stereotype name="Component"/>
							</UML:ModelElement.stereotype>
							<UML:ModelElement.taggedValue>
								<UML:TaggedValue tag="isSpecification" value="false"/>
								<UML:TaggedValue tag="ea_stype" value="Component"/>
								<UML:TaggedValue tag="ea_ntype" value="0"/>
								<UML:TaggedValue tag="version" value="1.0"/>
								<UML:TaggedValue tag="isActive" value="false"/>
								<UML:TaggedValue tag="package" value="EAPK_31369CB7_0938_42b0_A86E_1BA661D67FD7"/>
								<UML:TaggedValue tag="date_created" value="2014-05-13 12:15:42"/>
								<UML:TaggedValue tag="date_modified" value="2014-05-13 12:16:59"/>
								<UML:TaggedValue tag="gentype" value="Java"/>
								<UML:TaggedValue tag="tagged" value="0"/>
								<UML:TaggedValue tag="package_name" value="Component Model"/>
								<UML:TaggedValue tag="phase" value="1.0"/>
								<UML:TaggedValue tag="author" value="soo"/>
								<UML:TaggedValue tag="complexity" value="1"/>
								<UML:TaggedValue tag="status" value="Proposed"/>
								<UML:TaggedValue tag="stereotype" value="Component"/>
								<UML:TaggedValue tag="tpos" value="0"/>
								<UML:TaggedValue tag="ea_localid" value="47"/>
								<UML:TaggedValue tag="ea_eleType" value="element"/>
								<UML:TaggedValue tag="style" value="BackColor=-1;BorderColor=-1;BorderWidth=-1;FontColor=-1;VSwimLanes=1;HSwimLanes=1;BorderStyle=0;"/>
								<UML:TaggedValue tag="$ea_xref_property" value="$XREFPROP=$XID={59AD6087-2BE2-4a07-AB3E-3F5CB84CCF56}$XID;$NAM=Stereotypes$NAM;$TYP=element property$TYP;$VIS=Public$VIS;$PAR=0$PAR;$DES=@STEREO;Name=Component;GUID={CEA7330D-9939-4ee0-9716-B46C77A1DC3A};@ENDSTEREO;$DES;$CLT={CDF3BF72-3AC7-4349-A9F8-E4CA728FED28}$CLT;$SUP=&lt;none&gt;$SUP;$ENDXREF;"/>
							</UML:ModelElement.taggedValue>
						</UML:Component>
						<UML:Association xmi.id="EAID_3B502473_A579_4582_8529_488AF31428E2" visibility="public" isRoot="false" isLeaf="false" isAbstract="false" client="EAID_CDF3BF72_3AC7_4349_A9F8_E4CA728FED28" supplier="EAID_E14DC77C_0C77_4f33_AAC0_071536A15FA8">
							<UML:ModelElement.taggedValue>
								<UML:TaggedValue tag="style" value="3"/>
								<UML:TaggedValue tag="ea_type" value="Association"/>
								<UML:TaggedValue tag="direction" value="Unspecified"/>
								<UML:TaggedValue tag="linemode" value="3"/>
								<UML:TaggedValue tag="linecolor" value="-1"/>
								<UML:TaggedValue tag="linewidth" value="0"/>
								<UML:TaggedValue tag="seqno" value="0"/>
								<UML:TaggedValue tag="headStyle" value="0"/>
								<UML:TaggedValue tag="lineStyle" value="0"/>
								<UML:TaggedValue tag="ea_localid" value="31"/>
								<UML:TaggedValue tag="ea_sourceName" value="SourceFilter"/>
								<UML:TaggedValue tag="ea_targetName" value="Pipe"/>
								<UML:TaggedValue tag="ea_sourceType" value="Component"/>
								<UML:TaggedValue tag="ea_targetType" value="Component"/>
								<UML:TaggedValue tag="ea_sourceID" value="47"/>
								<UML:TaggedValue tag="ea_targetID" value="48"/>
								<UML:TaggedValue tag="virtualInheritance" value="0"/>
							</UML:ModelElement.taggedValue>
							<UML:Association.connection>
								<UML:AssociationEnd visibility="public" aggregation="none" isOrdered="false" targetScope="instance" changeable="none" isNavigable="true" type="EAID_CDF3BF72_3AC7_4349_A9F8_E4CA728FED28">
									<UML:ModelElement.taggedValue>
										<UML:TaggedValue tag="containment" value="Unspecified"/>
										<UML:TaggedValue tag="sourcestyle" value="Union=0;Derived=0;AllowDuplicates=0;Owned=0;Navigable=Unspecified;"/>
										<UML:TaggedValue tag="ea_end" value="source"/>
									</UML:ModelElement.taggedValue>
								</UML:AssociationEnd>
								<UML:AssociationEnd visibility="public" aggregation="none" isOrdered="false" targetScope="instance" changeable="none" isNavigable="true" type="EAID_E14DC77C_0C77_4f33_AAC0_071536A15FA8">
									<UML:ModelElement.taggedValue>
										<UML:TaggedValue tag="containment" value="Unspecified"/>
										<UML:TaggedValue tag="deststyle" value="Union=0;Derived=0;AllowDuplicates=0;Owned=0;Navigable=Unspecified;"/>
										<UML:TaggedValue tag="ea_end" value="target"/>
									</UML:ModelElement.taggedValue>
								</UML:AssociationEnd>
							</UML:Association.connection>
						</UML:Association>
						<UML:Component name="RegionBSinkFilter" xmi.id="EAID_D6018000_7990_45a4_8FC9_0793FFBC65B2" visibility="public" namespace="EAPK_31369CB7_0938_42b0_A86E_1BA661D67FD7" isRoot="false" isLeaf="false" isAbstract="false">
							<UML:ModelElement.stereotype>
								<UML:Stereotype name="Component"/>
							</UML:ModelElement.stereotype>
							<UML:ModelElement.taggedValue>
								<UML:TaggedValue tag="isSpecification" value="false"/>
								<UML:TaggedValue tag="ea_stype" value="Component"/>
								<UML:TaggedValue tag="ea_ntype" value="0"/>
								<UML:TaggedValue tag="version" value="1.0"/>
								<UML:TaggedValue tag="isActive" value="false"/>
								<UML:TaggedValue tag="package" value="EAPK_31369CB7_0938_42b0_A86E_1BA661D67FD7"/>
								<UML:TaggedValue tag="date_created" value="2014-05-13 12:16:36"/>
								<UML:TaggedValue tag="date_modified" value="2014-05-13 12:17:27"/>
								<UML:TaggedValue tag="gentype" value="Java"/>
								<UML:TaggedValue tag="tagged" value="0"/>
								<UML:TaggedValue tag="package_name" value="Component Model"/>
								<UML:TaggedValue tag="phase" value="1.0"/>
								<UML:TaggedValue tag="author" value="soo"/>
								<UML:TaggedValue tag="complexity" value="1"/>
								<UML:TaggedValue tag="status" value="Proposed"/>
								<UML:TaggedValue tag="stereotype" value="Component"/>
								<UML:TaggedValue tag="tpos" value="0"/>
								<UML:TaggedValue tag="ea_localid" value="55"/>
								<UML:TaggedValue tag="ea_eleType" value="element"/>
								<UML:TaggedValue tag="style" value="BackColor=-1;BorderColor=-1;BorderWidth=-1;FontColor=-1;VSwimLanes=1;HSwimLanes=1;BorderStyle=0;"/>
								<UML:TaggedValue tag="$ea_xref_property" value="$XREFPROP=$XID={1B6B1E38-29B4-46c4-8ED3-846CE16EE79F}$XID;$NAM=Stereotypes$NAM;$TYP=element property$TYP;$VIS=Public$VIS;$PAR=0$PAR;$DES=@STEREO;Name=Component;@ENDSTEREO;$DES;$CLT={D6018000-7990-45a4-8FC9-0793FFBC65B2}$CLT;$SUP=&lt;none&gt;$SUP;$ENDXREF;"/>
							</UML:ModelElement.taggedValue>
						</UML:Component>
						<UML:Connector name="Pipe" xmi.id="EAID_E14DC77C_0C77_4f33_AAC0_071536A15FA8" visibility="public" namespace="EAPK_31369CB7_0938_42b0_A86E_1BA661D67FD7" isRoot="false" isLeaf="false" isAbstract="false">
							<UML:ModelElement.stereotype>
								<UML:Stereotype name="Connector"/>
							</UML:ModelElement.stereotype>
							<UML:ModelElement.taggedValue>
								<UML:TaggedValue tag="isSpecification" value="false"/>
								<UML:TaggedValue tag="ea_stype" value="Component"/>
								<UML:TaggedValue tag="ea_ntype" value="0"/>
								<UML:TaggedValue tag="version" value="1.0"/>
								<UML:TaggedValue tag="isActive" value="false"/>
								<UML:TaggedValue tag="package" value="EAPK_31369CB7_0938_42b0_A86E_1BA661D67FD7"/>
								<UML:TaggedValue tag="date_created" value="2014-05-13 12:16:03"/>
								<UML:TaggedValue tag="date_modified" value="2014-05-13 12:16:53"/>
								<UML:TaggedValue tag="gentype" value="Java"/>
								<UML:TaggedValue tag="tagged" value="0"/>
								<UML:TaggedValue tag="package_name" value="Component Model"/>
								<UML:TaggedValue tag="phase" value="1.0"/>
								<UML:TaggedValue tag="author" value="soo"/>
								<UML:TaggedValue tag="complexity" value="1"/>
								<UML:TaggedValue tag="status" value="Proposed"/>
								<UML:TaggedValue tag="stereotype" value="Connector"/>
								<UML:TaggedValue tag="tpos" value="0"/>
								<UML:TaggedValue tag="ea_localid" value="48"/>
								<UML:TaggedValue tag="ea_eleType" value="element"/>
								<UML:TaggedValue tag="style" value="BackColor=-1;BorderColor=-1;BorderWidth=-1;FontColor=-1;VSwimLanes=1;HSwimLanes=1;BorderStyle=0;"/>
								<UML:TaggedValue tag="$ea_xref_property" value="$XREFPROP=$XID={6931F78D-C5ED-42c9-BC00-6A2B6EA1DA35}$XID;$NAM=Stereotypes$NAM;$TYP=element property$TYP;$VIS=Public$VIS;$PAR=0$PAR;$DES=@STEREO;Name=Connector;GUID={0E0CF230-66C9-4bc6-BC1A-188A48BE440C};@ENDSTEREO;$DES;$CLT={E14DC77C-0C77-4f33-AAC0-071536A15FA8}$CLT;$SUP=&lt;none&gt;$SUP;$ENDXREF;"/>
							</UML:ModelElement.taggedValue>
						</UML:Connector>
					</UML:Namespace.ownedElement>
				</UML:Type>
			</UML:Namespace.ownedElement>
		</UML:Model>
		<UML:Diagram name="Component Model" xmi.id="EAID_DB86337F_AF53_4530_B550_56A6E4066046" diagramType="ComponentDiagram" owner="EAPK_31369CB7_0938_42b0_A86E_1BA661D67FD7" toolName="Enterprise Architect 2.5">
			<UML:ModelElement.taggedValue>
				<UML:TaggedValue tag="version" value="1.0"/>
				<UML:TaggedValue tag="author" value="soo"/>
				<UML:TaggedValue tag="created_date" value="2005-11-19 00:00:00"/>
				<UML:TaggedValue tag="modified_date" value="2014-05-13 12:21:39"/>
				<UML:TaggedValue tag="package" value="EAPK_31369CB7_0938_42b0_A86E_1BA661D67FD7"/>
				<UML:TaggedValue tag="type" value="Component"/>
				<UML:TaggedValue tag="swimlanes" value="locked=false;orientation=0;width=0;inbar=false;names=false;color=0;bold=false;fcol=0;;cls=0;"/>
				<UML:TaggedValue tag="matrixitems" value="locked=false;matrixactive=false;swimlanesactive=true;width=1;"/>
				<UML:TaggedValue tag="ea_localid" value="4"/>
				<UML:TaggedValue tag="EAStyle" value="ShowPrivate=1;ShowProtected=1;ShowPublic=1;HideRelationships=0;Locked=0;Border=0;HighlightForeign=0;PackageContents=1;SequenceNotes=0;ScalePrintImage=0;PPgs.cx=0;PPgs.cy=0;DocSize.cx=827;DocSize.cy=1169;ShowDetails=0;Orientation=P;Zoom=100;ShowTags=0;OpParams=1;VisibleAttributeDetail=0;ShowOpRetType=1;ShowIcons=1;CollabNums=0;HideProps=0;ShowReqs=0;ShowCons=0;PaperSize=9;HideParents=0;UseAlias=0;HideAtts=0;HideOps=0;HideStereo=0;HideElemStereo=0;ShowTests=0;ShowMaint=0;ConnectorNotation=UML 2.0;ExplicitNavigability=0;AdvancedElementProps=1;AdvancedFeatureProps=1;AdvancedConnectorProps=1;ShowNotes=0;SuppressBrackets=0;SuppConnectorLabels=0;PrintPageHeadFoot=0;ShowAsList=0;"/>
				<UML:TaggedValue tag="styleex" value="SaveTag=10182A4F;ExcludeRTF=0;DocAll=0;HideQuals=0;AttPkg=1;ShowTests=0;ShowMaint=0;SuppressFOC=1;MatrixActive=0;SwimlanesActive=1;MatrixLineWidth=1;MatrixLocked=0;TConnectorNotation=UML 2.0;TExplicitNavigability=0;AdvancedElementProps=1;AdvancedFeatureProps=1;AdvancedConnectorProps=1;ProfileData=;MDGDgm=;STBLDgm=;ShowNotes=0;VisibleAttributeDetail=0;ShowOpRetType=1;SuppressBrackets=0;SuppConnectorLabels=0;PrintPageHeadFoot=0;ShowAsList=0;"/>
			</UML:ModelElement.taggedValue>
			<UML:Diagram.element>
				<UML:DiagramElement geometry="Left=1062;Top=417;Right=1172;Bottom=477;" subject="EAID_D6018000_7990_45a4_8FC9_0793FFBC65B2" seqno="1" style="DUID=697EB14A;"/>
				<UML:DiagramElement geometry="Left=836;Top=418;Right=946;Bottom=478;" subject="EAID_47743406_C904_4c4a_A09C_5AD9C4848CB6" seqno="2" style="DUID=697EB14A;"/>
				<UML:DiagramElement geometry="Left=615;Top=416;Right=725;Bottom=476;" subject="EAID_10EA6DFD_15B5_4de7_AA8D_E6E18301E274" seqno="3" style="DUID=697EB14A;"/>
				<UML:DiagramElement geometry="Left=389;Top=417;Right=499;Bottom=477;" subject="EAID_950B5493_F09B_401a_AFAA_C297AD96AB2E" seqno="4" style="DUID=697EB14A;"/>
				<UML:DiagramElement geometry="Left=1071;Top=210;Right=1181;Bottom=270;" subject="EAID_BE63FCEB_C8DF_4c7c_98A6_DB730CA80D42" seqno="5" style="DUID=697EB14A;"/>
				<UML:DiagramElement geometry="Left=845;Top=211;Right=955;Bottom=271;" subject="EAID_5BFC3086_2EA4_4908_890E_E6F601EEC73C" seqno="6" style="DUID=697EB14A;"/>
				<UML:DiagramElement geometry="Left=624;Top=209;Right=734;Bottom=269;" subject="EAID_669D5D5F_F9EB_4b1b_A50A_07799E4FCBE5" seqno="7" style="DUID=697EB14A;"/>
				<UML:DiagramElement geometry="Left=398;Top=210;Right=508;Bottom=270;" subject="EAID_E14DC77C_0C77_4f33_AAC0_071536A15FA8" seqno="8" style="DUID=697EB14A;"/>
				<UML:DiagramElement geometry="Left=179;Top=300;Right=289;Bottom=360;" subject="EAID_CDF3BF72_3AC7_4349_A9F8_E4CA728FED28" seqno="9" style="DUID=697EB14A;"/>
				<UML:DiagramElement geometry="SX=0;SY=0;EX=0;EY=0;EDGE=2;$LLB=;LLT=;LMT=;LMB=;LRT=;LRB=;IRHS=;ILHS=;Path=;" subject="EAID_59040C4C_F485_41e7_B05E_9FE5FC0C45FB" style="Mode=3;EOID=697EB14A;SOID=697EB14A;Color=-1;LWidth=0;Hidden=0;"/>
				<UML:DiagramElement geometry="SX=0;SY=0;EX=0;EY=0;EDGE=2;$LLB=;LLT=;LMT=;LMB=;LRT=;LRB=;IRHS=;ILHS=;Path=;" subject="EAID_36B9C420_1E2C_4507_924C_D97B45E9A480" style="Mode=3;EOID=697EB14A;SOID=697EB14A;Color=-1;LWidth=0;Hidden=0;"/>
				<UML:DiagramElement geometry="SX=0;SY=0;EX=0;EY=0;EDGE=2;$LLB=;LLT=;LMT=;LMB=;LRT=;LRB=;IRHS=;ILHS=;Path=;" subject="EAID_1C3002D7_1E88_4779_A1EC_635E509AFFD2" style="Mode=3;EOID=697EB14A;SOID=697EB14A;Color=-1;LWidth=0;Hidden=0;"/>
				<UML:DiagramElement geometry="SX=0;SY=0;EX=0;EY=0;EDGE=2;$LLB=;LLT=;LMT=;LMB=;LRT=;LRB=;IRHS=;ILHS=;Path=;" subject="EAID_3DD4086F_0665_4442_A9E8_8872D1243BE6" style="Mode=3;EOID=697EB14A;SOID=697EB14A;Color=-1;LWidth=0;Hidden=0;"/>
				<UML:DiagramElement geometry="SX=0;SY=0;EX=0;EY=0;EDGE=2;$LLB=;LLT=;LMT=;LMB=;LRT=;LRB=;IRHS=;ILHS=;Path=;" subject="EAID_7709F01B_C088_4d80_AA83_D51EDEEEBA8B" style="Mode=3;EOID=697EB14A;SOID=697EB14A;Color=-1;LWidth=0;Hidden=0;"/>
				<UML:DiagramElement geometry="SX=0;SY=0;EX=0;EY=0;EDGE=2;$LLB=;LLT=;LMT=;LMB=;LRT=;LRB=;IRHS=;ILHS=;Path=;" subject="EAID_E039CA5A_A07F_483c_94EE_FDCF2C522F93" style="Mode=3;EOID=697EB14A;SOID=697EB14A;Color=-1;LWidth=0;Hidden=0;"/>
				<UML:DiagramElement geometry="SX=0;SY=0;EX=0;EY=0;EDGE=3;$LLB=;LLT=;LMT=;LMB=;LRT=;LRB=;IRHS=;ILHS=;Path=;" subject="EAID_3B75DB1E_071F_41a4_B33E_B4817D84BC3B" style="Mode=3;EOID=697EB14A;SOID=697EB14A;Color=-1;LWidth=0;Hidden=0;"/>
				<UML:DiagramElement geometry="SX=0;SY=0;EX=0;EY=0;EDGE=2;$LLB=;LLT=;LMT=;LMB=;LRT=;LRB=;IRHS=;ILHS=;Path=;" subject="EAID_3B502473_A579_4582_8529_488AF31428E2" style="Mode=3;EOID=697EB14A;SOID=697EB14A;Color=-1;LWidth=0;Hidden=0;"/>
			</UML:Diagram.element>
		</UML:Diagram>
	</XMI.content>
	<XMI.difference/>
	<XMI.extensions xmi.extender="Enterprise Architect 2.5">
		<EAModel.paramSub/>
	</XMI.extensions>
</XMI>
